cp_lookup/__init__.py
cp_lookup/attachment/adcodes.csv
cp_lookup/classdefine.py
cp_lookup/mainfunc.py
cp_lookup/packagepath.py
cp_lookup/special.py
index_calmeth/__init__.py
index_calmeth/check_func.py
index_calmeth/evaluation.py
index_calmeth/non_dimension.py
index_calmeth/weights.py
Rh_s_PyTool-0.3.0.dist-info/WHEEL
Rh_s_PyTool-0.3.0.dist-info/METADATA
Rh_s_PyTool-0.3.0.dist-info/licenses/LICENSE
Rh_s_PyTool-0.3.0.dist-info/RECORD
