Metadata-Version: 2.1
Name: Rh-s-PyTool
Version: 0.3.0
Summary: 一系列Python工具的合集，用于中国省、市、区县三级行政区域的名称查询和补全、行政中心的经纬度查询、球面距离计算，同时也包含了综合指标评价方法的各种构成方法。
License: MIT
Author-email: skahanium <skahanium@gmail.com>
Requires-Python: >=3.10
Requires-Dist: jieba>=0.42.1
Requires-Dist: numba>=0.56.4
Requires-Dist: numpy>=1.23.1
Requires-Dist: polars>=0.14.0
Provides-Extra: others
Requires-Dist: notebook; extra == "others"
Requires-Dist: pandas>=1.4.3; extra == "others"
Project-URL: Documentation, https://skahanium.github.io/Rh-s-PyTool/
Project-URL: Github, https://github.com/skahanium/Rh-s-PyTool
